serptool/__init__.py
serptool/search_tool.py
serptool-0.1.2.dist-info/METADATA
serptool-0.1.2.dist-info/WHEEL
serptool-0.1.2.dist-info/RECORD
